{
  "annotations": {
    "changelogDate": "20260604181159"
  },
  "applications": ["ejemplo04"],
  "dto": "mapstruct",
  "fields": [
    {
      "fieldName": "numeroDocumento",
      "fieldType": "String",
      "fieldValidateRules": ["required", "maxlength"],
      "fieldValidateRulesMaxlength": "50"
    },
    {
      "fieldName": "primerNombre",
      "fieldType": "String",
      "fieldValidateRules": ["required", "maxlength"],
      "fieldValidateRulesMaxlength": "50"
    },
    {
      "fieldName": "segundoNombre",
      "fieldType": "String",
      "fieldValidateRules": ["maxlength"],
      "fieldValidateRulesMaxlength": "50"
    },
    {
      "fieldName": "primerApellido",
      "fieldType": "String",
      "fieldValidateRules": ["required", "maxlength"],
      "fieldValidateRulesMaxlength": "50"
    },
    {
      "fieldName": "segundoApellido",
      "fieldType": "String",
      "fieldValidateRules": ["maxlength"],
      "fieldValidateRulesMaxlength": "50"
    }
  ],
  "name": "Cuenta",
  "pagination": "pagination",
  "relationships": [
    {
      "otherEntityField": "login",
      "otherEntityName": "user",
      "relationshipName": "user",
      "relationshipSide": "left",
      "relationshipType": "one-to-one",
      "relationshipValidateRules": "required",
      "relationshipWithBuiltInEntity": true
    },
    {
      "otherEntityField": "nombreDocumento",
      "otherEntityName": "tipoDocumento",
      "relationshipName": "tipoDocumento",
      "relationshipSide": "right",
      "relationshipType": "many-to-one",
      "relationshipValidateRules": "required"
    }
  ],
  "searchEngine": "no",
  "service": "serviceImpl"
}
